github_metrics/__init__.py
github_metrics/common.py
github_metrics/helpers.py
github_metrics/request.py
github_metrics/run.py
github_metrics/settings.py
github_metrics/metrics/__init__.py
github_metrics/metrics/all.py
github_metrics/metrics/hotfixes_count.py
github_metrics/metrics/merge_rate.py
github_metrics/metrics/open_to_merge.py
github_metrics/metrics/pr_size.py
github_metrics/metrics/time_to_merge.py
github_metrics/metrics/time_to_open.py
github_metrics/metrics/time_to_review.py
github_metrics-0.0.10.dist-info/LICENSE
github_metrics-0.0.10.dist-info/METADATA
github_metrics-0.0.10.dist-info/WHEEL
github_metrics-0.0.10.dist-info/entry_points.txt
github_metrics-0.0.10.dist-info/top_level.txt
github_metrics-0.0.10.dist-info/RECORD
