Metadata-Version: 2.1
Name: github-metrics
Version: 0.0.10
Summary: Generate development metrics using github data for your project.
Home-page: https://github.com/vintasoftware/github-metrics
Author: Victoria Pantoja (Vinta Software)
Author-email: victoria.pantoja@vinta.com.br
License: MIT license
Platform: UNKNOWN
Classifier: Intended Audience :: Developers
Classifier: License :: OSI Approved :: MIT License
Classifier: Natural Language :: English
Classifier: Programming Language :: Python :: 3.8
Classifier: Programming Language :: Python :: 3.9
Requires-Python: >=3.8
Requires-Dist: arrow (==1.0.2)
Requires-Dist: click (==7.1.2)
Requires-Dist: numpy (==1.20.1)
Requires-Dist: python-decouple (==3.4)
Requires-Dist: requests (==2.22.0)
